{
  "version": "1.0",
  "defaultProvider": "cdnjs",
  "libraries": [
    {
      "library": "jquery-validate@1.19.5",
      "destination": "wwwroot/lib/jquery-validate/"
    },
    {
      "library": "jquery-validation-unobtrusive@4.0.0",
      "destination": "wwwroot/lib/jquery-validation-unobtrusive/"
    },
    {
      "provider": "unpkg",
      "library": "jquery-validation@1.19.5",
      "destination": "wwwroot/lib/jquery-validation/",
      "files": [
        "dist/additional-methods.min.js",
        "dist/jquery.validate.js",
        "LICENSE.md"
      ]
    }
  ]
}